{
  "version": "7",
  "dialect": "postgresql",
  "entries": [
    {
      "idx": 0,
      "version": "7",
      "when": 1721625293791,
      "tag": "0000_sloppy_blindfold",
      "breakpoints": true
    },
    {
      "idx": 1,
      "version": "7",
      "when": 1721634111176,
      "tag": "0001_cultured_bruce_banner",
      "breakpoints": true
    },
    {
      "idx": 2,
      "version": "7",
      "when": 1721636964851,
      "tag": "0002_volatile_roxanne_simpson",
      "breakpoints": true
    },
    {
      "idx": 3,
      "version": "7",
      "when": 1721661012041,
      "tag": "0003_marvelous_the_call",
      "breakpoints": true
    }
  ]
}